LICENSE
README.md
setup.cfg
setup.py
EMDA/__init__.py
EMDA/_version.py
EMDA/adders.py
EMDA/analysers.py
EMDA/calculators.py
EMDA/emda.py
EMDA/exceptions.py
EMDA/measure.py
EMDA/plotters.py
EMDA/runners.py
EMDA/selection.py
EMDA/testing.py
EMDA/tools.py
EasyMDA.egg-info/PKG-INFO
EasyMDA.egg-info/SOURCES.txt
EasyMDA.egg-info/dependency_links.txt
EasyMDA.egg-info/requires.txt
EasyMDA.egg-info/top_level.txt