Metadata-Version: 2.1
Name: EasyMDA
Version: 0.3.2
Summary: Easy MD Analysis (EMDA) is a Python package created with the aim of providing an easy, yet powerful way to perform analysis of MD simulations.
Home-page: https://github.com/MolBioMedUAB/EMDA
Download-URL: https://github.com/MolBioMedUAB/EMDA/archive/refs/tags/0.3.2.tar.gz
Author: Miquel Canyelles Niño
Author-email: mcanyellesnino@gmail.com
License: MIT
Keywords: biochemistry,simulations,MDAnalysis,molecular dynamics
Classifier: Programming Language :: Python :: 3
License-File: LICENSE
Requires-Dist: mdanalysis
Requires-Dist: tqdm
Requires-Dist: matplotlib
